setup.cfg
setup.py
django_doccloud.egg-info/PKG-INFO
django_doccloud.egg-info/SOURCES.txt
django_doccloud.egg-info/dependency_links.txt
django_doccloud.egg-info/requires.txt
django_doccloud.egg-info/top_level.txt
doccloud/__init__.py
doccloud/admin.py
doccloud/forms.py
doccloud/models.py
doccloud/tests.py
doccloud/urls.py
doccloud/views.py
doccloud/templates/doccloud-detail.html
doccloud/templates/doccloud-list.html
doccloud/templates/doccloud-upload.html