Metadata-Version: 1.0
Name: django-doccloud
Version: 0.5.0
Summary: Provides a reusable document app to add and edit files hosted by DocumentCloud
Home-page: http://github.com/BayCitizen/django-doccloud/
Author: Shane Shifflett
Author-email: shifflett.shane@gmail.com
License: UNKNOWN
Platform: UNKNOWN
Classifier: Development Status :: 3 - Alpha
Classifier: Environment :: Web Environment
Classifier: Framework :: Django
Classifier: Intended Audience :: Developers
Classifier: License :: OSI Approved :: Apache Software License
Classifier: Operating System :: OS Independent
Classifier: Programming Language :: Python
